afpy/__init__.py
afpy/cli.py
afpy/cwd.py
afpy/files.py
afpy/pathify.py
afpy/plot.py
afpy/string.py
afpy/yml.py
afpy-0.0.8.dist-info/LICENSE
afpy-0.0.8.dist-info/METADATA
afpy-0.0.8.dist-info/WHEEL
afpy-0.0.8.dist-info/top_level.txt
afpy-0.0.8.dist-info/RECORD
