Metadata-Version: 2.1
Name: afpy
Version: 0.0.8
Summary: A personal python package for increasing python efficiency by simplifying repeatable code.
Home-page: https://github.com/fordaj/afpy
Author: Andrew Ford
Author-email: author@example.com
License: UNKNOWN
Platform: UNKNOWN
Classifier: Programming Language :: Python :: 3
Classifier: License :: OSI Approved :: MIT License
Classifier: Operating System :: OS Independent
Requires-Python: >=3.6
License-File: LICENSE
